django_mongodb_engine/__init__.py
django_mongodb_engine/aggregations.py
django_mongodb_engine/base.py
django_mongodb_engine/compiler.py
django_mongodb_engine/creation.py
django_mongodb_engine/fields.py
django_mongodb_engine/models.py
django_mongodb_engine/query.py
django_mongodb_engine/router.py
django_mongodb_engine/south.py
django_mongodb_engine/south_adapter.py
django_mongodb_engine/storage.py
django_mongodb_engine/utils.py
django_mongodb_engine/contrib/__init__.py
django_mongodb_engine/contrib/search/__init__.py
django_mongodb_engine/contrib/search/fields.py
django_mongodb_engine/contrib/search/tokenizer.py
django_mongodb_engine/management/__init__.py
django_mongodb_engine/management/commands/__init__.py
django_mongodb_engine/management/commands/tellsiteid.py
django_mongodb_engine_py3-0.6.0.1.dist-info/DESCRIPTION.rst
django_mongodb_engine_py3-0.6.0.1.dist-info/METADATA
django_mongodb_engine_py3-0.6.0.1.dist-info/RECORD
django_mongodb_engine_py3-0.6.0.1.dist-info/WHEEL
django_mongodb_engine_py3-0.6.0.1.dist-info/metadata.json
django_mongodb_engine_py3-0.6.0.1.dist-info/top_level.txt
