Metadata-Version: 2.0
Name: django-mongodb-engine-py3
Version: 0.6.0.1
Summary: MongoDB backend for Django-nonrel
Home-page: http://django-nonrel.org/
Author: Flavio Percoco Premoli, Alberto Paro, Jonas Haag and contributors
Author-email: django-non-relational@googlegroups.com
License: 2-clause BSD
Platform: UNKNOWN
Classifier: Development Status :: 5 - Production/Stable
Classifier: Environment :: Web Environment
Classifier: Framework :: Django
Classifier: Intended Audience :: Developers
Classifier: License :: OSI Approved :: BSD License
Classifier: Operating System :: OS Independent
Classifier: Programming Language :: Python
Classifier: Programming Language :: Python :: 3.5
Classifier: Topic :: Database
Classifier: Topic :: Internet
Classifier: Topic :: Software Development :: Libraries :: Python Modules
Requires-Dist: djangotoolbox (>=1.6.0)
Requires-Dist: pymongo (>=2.8)
